README.md
setup.cfg
setup.py
indexer/__init__.py
indexer/base_indexer.py
indexer/utils.py
p1_indexer.egg-info/PKG-INFO
p1_indexer.egg-info/SOURCES.txt
p1_indexer.egg-info/dependency_links.txt
p1_indexer.egg-info/requires.txt
p1_indexer.egg-info/top_level.txt