Metadata-Version: 1.0
Name: p1-indexer
Version: 0.2.41951107
Summary: A package for indexer algolia
Home-page: https://github.com/jekidekoruma/p1-indexer
Author: Dekoruma
Author-email: hello@dekoruma.com
License: UNKNOWN
Platform: UNKNOWN
